{
  "verb": [
    {
      "description": "Act out (a past event)",
      "examples": [
        "bombers were gathered together to re-enact the historic first air attack"
      ],
      "synonyms": [
        "recreate",
        "build up a impression of",
        "build up a picture of",
        "form a impression of",
        "form a picture of",
        "piece together",
        "build up"
      ]
    },
    {
      "description": "Bring (a law) into effect again when the original statute has been repealed."
    }
  ],
  "pronounciation": "/ˌrēəˈnakt/",
  "audio": "https://s3.amazonaws.com/audio.oxforddictionaries.com/en/mp3/reenact_us_1.mp3"
}