{
  "noun": [
    {
      "description": "A fleet of ships or boats.",
      "examples": [
        "a flotilla of cargo boats"
      ],
      "synonyms": [
        "navy",
        "naval force",
        "task force",
        "naval task force",
        "armada",
        "squadron",
        "convoy",
        "column"
      ]
    }
  ],
  "origin": "Early 18th century: from Spanish, diminutive of flota fleet.",
  "pronounciation": "/floʊˈtɪlə/",
  "audio": "https://s3.amazonaws.com/audio.oxforddictionaries.com/en/mp3/flotilla_us_1.mp3"
}