{
  "noun": [
    {
      "description": "Courage in pain or adversity.",
      "examples": [
        "she endured her illness with great fortitude"
      ],
      "synonyms": [
        "courage",
        "bravery",
        "strength of mind",
        "strength of character",
        "moral strength",
        "toughness of spirit",
        "firmness of purpose",
        "strong-mindedness",
        "resilience",
        "backbone",
        "spine",
        "mettle",
        "spirit",
        "nerve",
        "pluck",
        "pluckiness",
        "doughtiness",
        "fearlessness",
        "valour",
        "intrepidity",
        "stout-heartedness",
        "endurance"
      ]
    }
  ],
  "origin": "Middle English: via French from Latin fortitudo, from fortis strong.",
  "pronounciation": "/ˈfɔrdəˌt(j)ud/",
  "audio": "https://s3.amazonaws.com/audio.oxforddictionaries.com/en/mp3/fortitude_us_1.mp3"
}