{
  "adjective": [
    {
      "description": "Wearing boots.",
      "examples": [
        "the crunching of snow beneath booted feet"
      ]
    },
    {
      "description": "(of a car) having a trunk of a specified type.",
      "examples": [
        "small booted cars"
      ]
    },
    {
      "description": "Unceremoniously forced to leave a place or job.",
      "examples": [
        "one lawmaker called on the Navy to rehire some of the booted sailors"
      ]
    }
  ],
  "pronounciation": "/ˈbo͞odəd/",
  "audio": "https://s3.amazonaws.com/audio.oxforddictionaries.com/en/mp3/booted_us_2.mp3"
}