{
  "noun": [
    {
      "description": "A broth made by stewing meat, fish, or vegetables in water.",
      "examples": [],
      "synonyms": [
        "stock",
        "broth",
        "juice",
        "gravy",
        "liquid",
        "infusion",
        "extract",
        "concentrate",
        "decoction"
      ]
    }
  ],
  "origin": "French, literally liquid in which something has boiled, from bouillir to boil.",
  "pronounciation": "/ˈbo͞o(l)yän/",
  "audio": "https://s3.amazonaws.com/audio.oxforddictionaries.com/en/mp3/bouillon_us_1.mp3"
}