{
  "adjective": [
    {
      "description": "Relating to or characteristic of the German composer and pianist Johannes Brahms or his work.",
      "examples": [
        "a Brahmsian melody pours forth"
      ]
    }
  ],
  "noun": [
    {
      "description": "An admirer of the German composer and pianist Johannes Brahms or his work.",
      "examples": [
        "many Brahmsians have told me that one day I will begin to appreciate the beauties of his music"
      ]
    }
  ],
  "pronounciation": "/ˈbrämzēən/",
  "audio": "https://s3.amazonaws.com/audio.oxforddictionaries.com/en/mp3/brahmsian_1_us_1.mp3"
}