{
  "verb": [
    {
      "description": "Take air into the lungs and then expel it, especially as a regular physiological process.",
      "examples": [
        "breathe in through your nose",
        "he breathed out heavily",
        "we are polluting the air we breathe",
        "she was wheezing as she breathed"
      ],
      "synonyms": [
        "inhale and exhale",
        "respire",
        "draw breath"
      ]
    }
  ],
  "phrases": [
    "she wouldn't breathe freely again until she was airborne",
    "Shutting the door behind her, she began breathing again.",
    "It felt like hours before he could breathe again, before he could relax his jaw and focus.",
    "They relax her and she feels like she can breathe again.",
    "I tried to restrain my thoughts and truly relax to some extent where I could breathe again."
  ],
  "origin": "Middle English (in the sense exhale, steam): from breath.",
  "pronounciation": "/brið/",
  "audio": "https://s3.amazonaws.com/audio.oxforddictionaries.com/en/mp3/breathe_us_1.mp3"
}