{
  "noun": [
    {
      "description": "Pretentious and vulgar display, especially of wealth and luxury, intended to impress or attract notice.",
      "examples": [
        "the office was spacious, but without any trace of ostentation"
      ],
      "synonyms": [
        "showiness",
        "show",
        "showing off",
        "ostentatiousness"
      ]
    }
  ],
  "origin": "Late Middle English: via Old French from Latin ostentatio(n-), from the verb ostentare, frequentative of ostendere stretch out to view.",
  "pronounciation": "/ˌästənˈtāSHən/",
  "audio": "https://s3.amazonaws.com/audio.oxforddictionaries.com/en/mp3/ostentation_us_1.mp3"
}