{
  "noun": [
    {
      "description": "A joining or merging of different parts or qualities in which the component elements are individually distinct.",
      "examples": [
        "this color combination is stunningly effective",
        "a combination of blackberries, raspberries, and rhubarb"
      ],
      "synonyms": [
        "amalgamation",
        "amalgam",
        "merger",
        "union",
        "blend",
        "mixture",
        "mix",
        "mingling",
        "meld",
        "fusion",
        "fusing",
        "compound",
        "alloy",
        "marriage",
        "weave",
        "coalescence",
        "coalition",
        "pooling",
        "integration",
        "conjunction",
        "incorporation",
        "synthesis",
        "composite",
        "composition",
        "concoction"
      ]
    },
    {
      "description": "A sequence of numbers or letters used to open a combination lock.",
      "examples": [
        "a combination briefcase"
      ]
    },
    {
      "description": "A selection of a given number of elements from a larger number without regard to their arrangement.",
      "examples": []
    }
  ],
  "origin": "Late Middle English: from late Latin combinatio(n-), from the verb combinare join two by two (see combine).",
  "pronounciation": "/ˌkɑmbəˈneɪʃ(ə)n/",
  "audio": "https://s3.amazonaws.com/audio.oxforddictionaries.com/en/mp3/combination_us_1.mp3"
}