{
  "adjective": [
    {
      "description": "(of food or a meal) prepared by heating.",
      "examples": [
        "a cooked breakfast",
        "cooked chicken can last longer than two days when stored properly"
      ]
    },
    {
      "description": "Altered dishonestly; falsified.",
      "examples": [
        "as the result of cooked books, stock prices soared"
      ]
    }
  ],
  "pronounciation": "/kʊkt/",
  "audio": "https://s3.amazonaws.com/audio.oxforddictionaries.com/en/mp3/cooked_us_1.mp3"
}