{
  "adjective": [
    {
      "description": "(of a window or doorframe or similar structure) fitted with panes of glass.",
      "examples": [
        "bookcases with glazed doors"
      ]
    },
    {
      "description": "(of food, fabric, etc.) overlaid or covered with a smooth, shiny coating or finish.",
      "examples": [
        "glazed shallots",
        "a large glazed urn"
      ]
    },
    {
      "description": "(of a person's eyes or expression) showing no interest or animation.",
      "examples": [
        "she had a glazed look in her eyes"
      ]
    }
  ],
  "pronounciation": "/ɡleɪzd/",
  "audio": "https://s3.amazonaws.com/audio.oxforddictionaries.com/en/mp3/glazed_us_2.mp3"
}