{
  "noun": [
    {
      "description": "A real or imagined wrong or other cause for complaint or protest, especially unfair treatment.",
      "examples": [
        "failure to redress genuine grievances"
      ],
      "synonyms": [
        "injustice",
        "unjust act",
        "wrong",
        "injury",
        "ill",
        "offence",
        "disservice",
        "unfairness",
        "evil",
        "outrage",
        "atrocity",
        "damage"
      ]
    }
  ],
  "origin": "Middle English (also in the sense injury): from Old French grevance, from grever to burden (see grieve).",
  "pronounciation": "/ˈɡrivəns/",
  "audio": "https://s3.amazonaws.com/audio.oxforddictionaries.com/en/mp3/grievance_us_1.mp3"
}