{
  "adjective": [
    {
      "description": "Relating to a state governor or the office of state governor.",
      "examples": [
        "a gubernatorial election"
      ],
      "synonyms": [
        "managerial",
        "management",
        "directorial",
        "directing",
        "executive",
        "organizational",
        "controlling",
        "governmental",
        "supervisory",
        "regulatory"
      ]
    }
  ],
  "origin": "Mid 18th century: from Latin gubernator governor (from gubernare steer, govern, from Greek kubernan to steer) + -ial.",
  "pronounciation": "/ˌɡubərnəˈtɔriəl/",
  "audio": "https://s3.amazonaws.com/audio.oxforddictionaries.com/en/mp3/gubernatorial_us_1.mp3"
}