{
  "verb": [
    {
      "description": "Make (someone or something) accept something as normal or usual.",
      "examples": [
        "I accustomed my eyes to the lenses",
        "they tried to accustom him to their lighthearted ways"
      ],
      "synonyms": [
        "adapt",
        "adjust",
        "acclimatize",
        "attune",
        "habituate",
        "accommodate",
        "assimilate",
        "acculturate",
        "inure",
        "harden",
        "condition",
        "reconcile",
        "become resigned",
        "resign"
      ]
    }
  ],
  "origin": "Late Middle English: from Old French acostumer, from a- (from Latin ad to, at) + costume custom.",
  "pronounciation": "/əˈkəstəm/",
  "audio": "https://s3.amazonaws.com/audio.oxforddictionaries.com/en/mp3/accustom_us_1.mp3"
}