{
  "plural noun": [
    {
      "description": "The members of a heretical sect in southern France in the 12th–13th centuries, identified with the Cathars. Their teaching was a form of Manichaean dualism, with an extremely strict moral and social code.",
      "examples": []
    }
  ],
  "origin": "From medieval Latin, from Albiga, the Latin name of Albi in southern France.",
  "pronounciation": "/ˌælbəˈdʒɛnsiz/",
  "audio": "https://s3.amazonaws.com/audio.oxforddictionaries.com/en/mp3/albigenses_1_us_1.mp3"
}