{
  "verb": [
    {
      "description": "Cause (someone) to feel isolated or estranged.",
      "examples": [
        "an urban environment that would alienate its inhabitants"
      ],
      "synonyms": [
        "estrange",
        "turn away",
        "set apart",
        "drive apart",
        "isolate",
        "detach",
        "distance",
        "put at a distance"
      ]
    },
    {
      "description": "Transfer ownership of (property rights) to another person or group.",
      "synonyms": [
        "transfer",
        "convey",
        "pass on",
        "hand over",
        "devolve"
      ]
    }
  ],
  "phrases": [
    "The waif seemed eager to get inside, but I didn't want to alienate her affections if she had a home.",
    "The young man, in his efforts to extricate the young woman from her problems, manages to alienate her affections while arousing the enmity of her powerful protector.",
    "That modest discovery, with the consequent madness of incessant composition, alienated my affections from the hospital.",
    "Dr. Chapin never attempted in any way to alienate my affections from father.",
    "Austerity and sternness will alienate his affections, and severe words will sting him to the quick."
  ],
  "origin": "Early 16th century: from Latin alienat- estranged, from the verb alienare, from alienus of another (see alien).",
  "pronounciation": "/ˈeɪljəˌneɪt/",
  "audio": "https://s3.amazonaws.com/audio.oxforddictionaries.com/en/mp3/alienate_us_1.mp3"
}