{
  "pronoun": [
    {
      "description": "Used to refer to a thing, no matter what.",
      "examples": [
        "nobody was saying anything",
        "have you found anything?",
        "he inquired whether there was anything he could do"
      ]
    }
  ],
  "phrases": [
    "this grisly ending is anything but sentimental",
    "Such a fight Warren would be crazy to pass up, and he is anything but crazy.",
    "The Fulford campaign proves that a community threatened is anything but apathetic.",
    "It may have been a charity match but the boys in Green were going to be anything but a walkover.",
    "Not in a sentimental sense, for a child is anything but that, but in a very factual way."
  ],
  "pronounciation": "/ˈenēˌTHiNG/",
  "audio": "https://s3.amazonaws.com/audio.oxforddictionaries.com/en/mp3/anything_us_1.mp3"
}