{
  "noun": [
    {
      "description": "The loss of a sound or sounds at the end of a word, e.g., in the derivation of curio from curiosity.",
      "examples": [],
      "synonyms": [
        "leaving out",
        "exclusion",
        "exception",
        "non-inclusion",
        "deletion",
        "erasure",
        "cut",
        "excision",
        "elimination",
        "absence"
      ]
    }
  ],
  "origin": "Mid 16th century: from late Latin, from Greek apokoptein cut off, from apo- from + koptein to cut.",
  "pronounciation": "/əˈpäkəpē/",
  "audio": "https://s3.amazonaws.com/audio.oxforddictionaries.com/en/mp3/apocope_us_1.mp3"
}