{
  "noun": [
    {
      "description": "The positioning of things or the condition of being side by side or close together.",
      "examples": []
    },
    {
      "description": "A relationship between two or more words or phrases in which the two units are grammatically parallel and have the same referent (e.g. my friend Sue; the first US president, George Washington).",
      "examples": []
    }
  ],
  "origin": "Late Middle English: from late Latin appositio(n-), from apponere to apply (see apposite).",
  "pronounciation": "/ˌapəˈziSH(ə)n/",
  "audio": "https://s3.amazonaws.com/audio.oxforddictionaries.com/en/mp3/apposition_us_1.mp3"
}