{
  "noun": [
    {
      "description": "Extreme greed for wealth or material gain.",
      "examples": [
        "he was rich beyond the dreams of avarice"
      ],
      "synonyms": [
        "greed",
        "acquisitiveness",
        "cupidity",
        "covetousness",
        "avariciousness",
        "rapacity",
        "rapaciousness",
        "graspingness",
        "materialism",
        "mercenariness"
      ]
    }
  ],
  "origin": "Middle English: from Old French, from Latin avaritia, from avarus greedy.",
  "pronounciation": "/ˈævərəs/",
  "audio": "https://s3.amazonaws.com/audio.oxforddictionaries.com/en/mp3/avarice_us_1.mp3"
}