{
  "adjective": [
    {
      "description": "(of language or social behavior) not characteristic of the upper social classes; not socially acceptable to certain people.",
      "examples": [
        "he's always teasing her for her Cockney accent and her non-U turns of phrase"
      ],
      "synonyms": [
        "uncultured",
        "uncultivated",
        "unrefined",
        "lowbrow",
        "philistine",
        "uneducated",
        "unpolished",
        "provincial",
        "rustic"
      ]
    }
  ],
  "origin": "1950s: from non- + U.",
  "pronounciation": "/nɑnˈju/",
  "audio": "https://s3.amazonaws.com/audio.oxforddictionaries.com/en/mp3/non_u_1_us_2.mp3"
}