{
  "verb": [
    {
      "description": "Fail to fulfill the hopes or expectations of (someone)",
      "examples": [
        "I have no wish to disappoint everyone by postponing the visit"
      ],
      "synonyms": [
        "let down",
        "fail",
        "dash the hopes of"
      ]
    }
  ],
  "origin": "Late Middle English (in the sense deprive of a position): from Old French desappointer.",
  "pronounciation": "/ˌdɪsəˈpɔɪnt/",
  "audio": "https://s3.amazonaws.com/audio.oxforddictionaries.com/en/mp3/disappoint_us_3.mp3"
}