{
  "adjective": [
    {
      "description": "Inclined to lay down principles as incontrovertibly true.",
      "examples": [
        "he gives his opinion without trying to be dogmatic"
      ],
      "synonyms": [
        "opinionated",
        "peremptory",
        "assertive",
        "imperative",
        "insistent",
        "emphatic",
        "adamant",
        "doctrinaire",
        "authoritarian",
        "authoritative",
        "domineering",
        "imperious",
        "high-handed",
        "pontifical",
        "arrogant",
        "overbearing",
        "dictatorial",
        "uncompromising",
        "unyielding",
        "unbending",
        "inflexible",
        "rigid",
        "entrenched",
        "unquestionable",
        "unchallengeable"
      ]
    }
  ],
  "origin": "Early 17th century (as a noun denoting a philosopher or physician of a school based on a priori assumptions): via late Latin from Greek dogmatikos, from dogma, dogmat- (see dogma).",
  "pronounciation": "/dɔɡˈmædɪk/",
  "audio": "https://s3.amazonaws.com/audio.oxforddictionaries.com/en/mp3/dogmatic_us_2_rr.mp3"
}