{
  "adjective": [
    {
      "description": "Relating to or characteristic of the ancient region of Scythia or its inhabitants.",
      "examples": [
        "the formation of the Scythian cultures"
      ]
    }
  ],
  "noun": [
    {
      "description": "A native or inhabitant of the ancient region of Scythia.",
      "examples": [
        "the Scythians retreated into the Crimea"
      ]
    }
  ],
  "pronounciation": "/ˈsiTHēən/",
  "audio": "https://s3.amazonaws.com/audio.oxforddictionaries.com/en/mp3/scythian_1_us_1.mp3"
}