{
  "noun": [
    {
      "description": "The action of subjecting a country or person to one's control, or the fact of being subjected.",
      "examples": [
        "the country's subjection to European colonialism"
      ],
      "synonyms": [
        "subjugation",
        "domination",
        "oppression",
        "control",
        "mastery",
        "repression",
        "suppression",
        "bondage",
        "slavery",
        "enslavement",
        "persecution",
        "exploitation",
        "abuse"
      ]
    }
  ],
  "pronounciation": "/səbˈjekSH(ə)n/",
  "audio": "https://s3.amazonaws.com/audio.oxforddictionaries.com/en/mp3/subjection_us_1.mp3"
}