{
  "noun": [
    {
      "description": "A tiny piece of a substance.",
      "examples": [
        "the tiniest mote of dust"
      ],
      "synonyms": [
        "speck",
        "particle",
        "grain",
        "spot",
        "fleck",
        "atom",
        "scintilla",
        "mite"
      ]
    }
  ],
  "phrases": [
    "I despise how easily these extremists strive to pluck the mote out of someone else's eye while leaving the well-rooted tree that's in their own.",
    "Look at the mote in your own eye first, congressman.",
    "If this fight is only to be a yelling match about the motes in each other's eyes I am not interested in participating.",
    "So East had a mote in his eye and was fortunate that his partner did not notice it.",
    "And to the British and European hypocrites who thought this was a good idea, I say remove the beam from your own eye before taking the mote from my eye."
  ],
  "origin": "Old English mot, related to Dutch mot dust, sawdust.",
  "pronounciation": "/moʊt/",
  "audio": "https://s3.amazonaws.com/audio.oxforddictionaries.com/en/mp3/mote_us_1.mp3"
}