{
  "noun": [
    {
      "description": "A public entertainment consisting of a procession of people in elaborate, colorful costumes, or an outdoor performance of a historical scene.",
      "synonyms": [
        "parade",
        "procession",
        "cavalcade",
        "scene",
        "play",
        "representation",
        "tableau",
        "tableau vivant"
      ]
    }
  ],
  "origin": "Late Middle English pagyn, of unknown origin.",
  "pronounciation": "/ˈpædʒənt/",
  "audio": "https://s3.amazonaws.com/audio.oxforddictionaries.com/en/mp3/pageant_us_1.mp3"
}