{
  "adjective": [
    {
      "description": "Not feeling shame or regret about one's actions or attitudes.",
      "examples": [
        "impenitent elitists"
      ],
      "synonyms": [
        "unrepentant",
        "unrepenting",
        "without regret",
        "without remorse",
        "uncontrite",
        "remorseless",
        "unremorseful",
        "shameless",
        "unashamed",
        "unblushing",
        "unapologetic",
        "unabashed",
        "brazen",
        "conscienceless"
      ]
    }
  ],
  "origin": "Late Middle English: from ecclesiastical Latin impaenitent- not repenting, from Latin in- not + paenitere repent.",
  "pronounciation": "/imˈpenətnt/",
  "audio": "https://s3.amazonaws.com/audio.oxforddictionaries.com/en/mp3/impenitent_us_1.mp3"
}