{
  "adjective": [
    {
      "description": "Without compassion for misery or suffering; cruel.",
      "examples": [
        "confining wild horses is inhumane"
      ],
      "synonyms": [
        "cruel",
        "harsh",
        "brutal",
        "callous",
        "sadistic",
        "severe",
        "savage",
        "vicious",
        "barbaric",
        "barbarous"
      ]
    }
  ],
  "origin": "Late Middle English (in the sense inhuman, brutal): originally a variant of inhuman (rare after 1700); in modern use from in- not + humane (the current sense dating from the early 19th century).",
  "pronounciation": "/ˌɪn(h)juˈmeɪn/",
  "audio": "https://s3.amazonaws.com/audio.oxforddictionaries.com/en/mp3/inhumane_us_1.mp3"
}