{
  "verb": [
    {
      "description": "Make or become accustomed or used to something.",
      "examples": [
        "she had habituated the chimps to humans"
      ],
      "synonyms": [
        "accustom",
        "make used",
        "adapt",
        "adjust",
        "attune",
        "acclimatize",
        "acculturate",
        "inure",
        "harden"
      ]
    }
  ],
  "origin": "Late 15th century: from late Latin habituat- accustomed, from the verb habituare, from habitus (see habit).",
  "pronounciation": "/həˈbiCHəˌwāt/",
  "audio": "https://s3.amazonaws.com/audio.oxforddictionaries.com/en/mp3/habituate_us_1.mp3"
}