{
  "noun": [
    {
      "description": "An angry and embittered state of mind, felt but not openly expressed; rankling jealousy, resentment, or discontent."
    },
    {
      "description": "In plural Feelings of jealousy, resentment, or bitterness; grudges."
    }
  ],
  "adjective": [
    {
      "description": "That arouses strong emotions, especially jealousy, bitterness, or resentment; resulting from or characterized by such emotions. Of an emotion: painfully sharp or intense; deeply felt."
    }
  ],
  "origin": "Late Middle English; earliest use found in The Laud Troy Book. From heart + burning&lt;br&gt;late 16th century; earliest use found in Edmund Spenser (?1552–1599), poet and administrator in Ireland. From heart + burning, probably after heart-burn, heart-burning.",
  "pronounciation": "/ˈhɑːtˌbəːnɪŋ/"
}