{
  "noun": [
    {
      "description": "The quality or state of being hesitant.",
      "examples": [
        "Jackson took advantage of some hesitancy in the defense to rifle in a shot"
      ],
      "synonyms": [
        "uncertainty",
        "hesitation",
        "hesitance",
        "unsureness",
        "doubt",
        "doubtfulness",
        "dubiousness",
        "irresolution",
        "irresoluteness",
        "indecision",
        "indecisiveness",
        "equivocation",
        "vacillation",
        "wavering",
        "scepticism",
        "nervousness",
        "second thoughts"
      ]
    }
  ],
  "pronounciation": "/ˈhezidənsē/",
  "audio": "https://s3.amazonaws.com/audio.oxforddictionaries.com/en/mp3/hesitancy_us_2.mp3"
}