{
  "noun": [
    {
      "description": "The action of breaking into a building, especially in daytime, to commit a crime.",
      "synonyms": [
        "burglary",
        "theft",
        "thievery",
        "stealing",
        "breaking and entering",
        "larceny",
        "shoplifting",
        "pilfering",
        "filching",
        "embezzlement",
        "misappropriation",
        "swindling",
        "fraud"
      ]
    }
  ],
  "pronounciation": "/ˈhaʊsˌbreɪkɪŋ/",
  "audio": "https://s3.amazonaws.com/audio.oxforddictionaries.com/en/mp3/housebreaking_us_1.mp3"
}