{
  "verb": [
    {
      "description": "Make or become straight from a bent or twisted form or position.",
      "examples": [
        "I had trouble unbending my cramped knees",
        "he unbent from the cockpit as she passed"
      ],
      "synonyms": [
        "straighten",
        "straighten out",
        "extend",
        "flex",
        "uncurl",
        "flatten"
      ]
    },
    {
      "description": "Unfasten (sails) from yards and stays."
    }
  ],
  "pronounciation": "/ˌənˈbɛnd/",
  "audio": "https://s3.amazonaws.com/audio.oxforddictionaries.com/en/mp3/unbend_us_1.mp3"
}