{
  "adjective": [
    {
      "description": "Not having or showing good judgment or taste.",
      "synonyms": [
        "boorish",
        "loutish",
        "oafish",
        "thuggish",
        "brutish",
        "bearish",
        "neanderthal",
        "philistine",
        "coarse",
        "uncouth",
        "unsavoury",
        "crass",
        "vulgar",
        "common",
        "unrefined",
        "unsophisticated",
        "uncultured",
        "uncultivated",
        "tasteless",
        "insensitive",
        "unfeeling",
        "imperceptive",
        "callous"
      ]
    }
  ],
  "pronounciation": "/ˌəndɪsˈkrɪməˌneɪdɪŋ/",
  "audio": "https://s3.amazonaws.com/audio.oxforddictionaries.com/en/mp3/undiscriminating_us_1.mp3"
}