{
  "noun": [
    {
      "description": "A person who has risen suddenly to wealth or high position, especially one who behaves arrogantly.",
      "examples": [
        "the upstarts who dare to challenge the legitimacy of his rule",
        "an upstart leader"
      ],
      "synonyms": [
        "parvenu",
        "parvenue",
        "arriviste",
        "nouveau riche",
        "vulgarian"
      ]
    }
  ],
  "pronounciation": "/ˈəpˌstɑrt/",
  "audio": "https://s3.amazonaws.com/audio.oxforddictionaries.com/en/mp3/upstart_us_1.mp3"
}